odoo/addons/base_user_role_profile/README.rst
odoo/addons/base_user_role_profile/__init__.py
odoo/addons/base_user_role_profile/__manifest__.py
odoo/addons/base_user_role_profile/hooks.py
odoo/addons/base_user_role_profile/data/data.xml
odoo/addons/base_user_role_profile/i18n/base_user_role_profile.pot
odoo/addons/base_user_role_profile/i18n/fr.po
odoo/addons/base_user_role_profile/i18n/it.po
odoo/addons/base_user_role_profile/models/__init__.py
odoo/addons/base_user_role_profile/models/ir_http.py
odoo/addons/base_user_role_profile/models/profile.py
odoo/addons/base_user_role_profile/models/role.py
odoo/addons/base_user_role_profile/models/user.py
odoo/addons/base_user_role_profile/readme/CONFIGURE.rst
odoo/addons/base_user_role_profile/readme/CONTRIBUTORS.rst
odoo/addons/base_user_role_profile/readme/DESCRIPTION.rst
odoo/addons/base_user_role_profile/readme/USAGE.rst
odoo/addons/base_user_role_profile/security/ir.model.access.csv
odoo/addons/base_user_role_profile/static/description/icon.png
odoo/addons/base_user_role_profile/static/description/index.html
odoo/addons/base_user_role_profile/tests/__init__.py
odoo/addons/base_user_role_profile/tests/test_user_role.py
odoo/addons/base_user_role_profile/views/assets.xml
odoo/addons/base_user_role_profile/views/profile.xml
odoo/addons/base_user_role_profile/views/role.xml
odoo/addons/base_user_role_profile/views/user.xml
odoo14_addon_base_user_role_profile-14.0.1.1.0.dist-info/METADATA
odoo14_addon_base_user_role_profile-14.0.1.1.0.dist-info/WHEEL
odoo14_addon_base_user_role_profile-14.0.1.1.0.dist-info/top_level.txt
odoo14_addon_base_user_role_profile-14.0.1.1.0.dist-info/RECORD
